pyostracker/__init__.py
pyostracker/test_lib.py
pyostracker-0.0.3.dist-info/LICENSE
pyostracker-0.0.3.dist-info/METADATA
pyostracker-0.0.3.dist-info/WHEEL
pyostracker-0.0.3.dist-info/top_level.txt
pyostracker-0.0.3.dist-info/RECORD
