Metadata-Version: 2.1
Name: pyostracker
Version: 0.0.3
Summary: Python client library for ostracker.xyz
Home-page: https://ostracker.xyz
Author: ostracker.xyz
Author-email: admin@ostracker.xyz
License: UNKNOWN
Platform: UNKNOWN
Requires-Python: >=3.6
